uart/backup/uart.v
`default_nettype none

module uart
#(
    parameter CYCLES_PER_BIT = 234
)
(
    input clk,
    input uartRx,
    output reg uartTx,
    output reg [5:0] led,
    input btn1
);

localparam CYCLES_PER_READ = (CYCLES_PER_BIT/2); // read at the middle of a bit in case of clock wonkyness
// rx registers
reg [3:0] rxState = 0; // state of the uart state machine
reg [12:0] rxCounter = 0; // number of clock cycle in current rx
reg [2:0] rxBitNumber = 0; // number of rx data bits read since start bit
reg [7:0] dataIn = 0; // 8 bit uart rx data
reg [7:0] data = 0;
reg rxParity = 0; // parity flip per 1 this is for odd parity
reg byteGood = 0; // if passes parity check
reg byteReady = 0; // if all the 8 bits of rx are read or nah

localparam RX_STATE_IDLE = 0;
localparam RX_STATE_START_BIT = 1;
localparam RX_STATE_READ_WAIT = 2;
localparam RX_STATE_READ = 3;
localparam RX_STATE_PARITY_BIT = 5;
localparam RX_STATE_STOP_BIT = 6;

// TX registers
reg [3:0] txState = 0; // state of the uart state machine
reg [12:0] txCounter = 0; // number of clock cycle in current tx
reg [2:0] txBitNumber = 0; // number of tx data bits sent since start bit
reg [7:0] txData = 'b10101010;
reg txParity = 0; // parity flip per 1 this is for even parity
reg txDataReady = 0; // if we have tx data to send over
reg txByteDone = 0; // if we finished sending over the data

localparam  TX_STATE_IDLE = 0;
localparam  TX_STATE_START_BIT = 1;
localparam  TX_STATE_SEND_WAIT = 2;
localparam  TX_STATE_SEND = 3;
localparam  TX_STATE_PARITY_BIT = 5;
localparam  TX_STATE_STOP_BIT = 6;
localparam  TX_STATE_STOP_DELAY = 7; // aka stop bit end delay to allow for the other side to process


always @(posedge clk) begin
    case (rxState)
        RX_STATE_IDLE: begin
            if (uartRx == 0) begin // reset if it's pulled low
                rxState <= RX_STATE_START_BIT;
                rxCounter <= 1; // we start the read clock counter
                rxBitNumber <= 0;
                byteReady <= 0; // no data is indeed not ready
                byteGood <= 0; // we don't know if the data is good or not
                rxParity <= 0; // reset parity
            end
        end
        RX_STATE_START_BIT: begin
            if (rxCounter == CYCLES_PER_READ) begin
                rxState <= RX_STATE_READ_WAIT;
                rxCounter <= 1;
                dataIn <= 0;
            end else
                rxCounter <= rxCounter + 1;
        end
        RX_STATE_READ_WAIT: begin
            rxCounter<= rxCounter +1;
            if ((rxCounter+1) == CYCLES_PER_BIT) begin
                rxState <= RX_STATE_READ;
            end
        end
        RX_STATE_READ: begin
            rxCounter <= 1;
            dataIn <= {uartRx, dataIn[7:1]};
            rxBitNumber <= rxBitNumber + 1;
            if (uartRx==1) begin
                rxParity <= ~rxParity;
            end
            if (rxBitNumber == 7) begin
                rxState <= RX_STATE_PARITY_BIT;
                // // rxState <= RX_STATE_STOP_BIT; // no parity bit
            end else
                rxState <= RX_STATE_READ_WAIT;
        end
        RX_STATE_PARITY_BIT: begin
            rxCounter <= rxCounter + 1;
            if (rxCounter==CYCLES_PER_BIT) begin
                if (uartRx == rxParity) begin
                    byteGood <= 1;
                end
                rxState <= RX_STATE_STOP_BIT;
                rxCounter <= 1;
            end
        end
        RX_STATE_STOP_BIT: begin
            rxCounter <= rxCounter + 1;
            if (rxCounter == CYCLES_PER_BIT) begin
                rxState <= RX_STATE_IDLE;
                byteReady <= 1;
                rxCounter <= 1;
                if (byteGood) begin
                    data <= dataIn;
                end else begin
                    data <= 0;
                end
            end
        end
    endcase
end
always @(posedge clk) begin
    case (txState)
        TX_STATE_IDLE: begin
            uartTx <= 1;
            if (txDataReady) begin
                txState <= TX_STATE_START_BIT;
                txCounter <= 1;
                txBitNumber <= 0;
                txByteDone <= 0;
                txParity <= 0;
            end
        end
        TX_STATE_START_BIT: begin
            // txState <= TX_STATE_SEND_WAIT;
            // txCounter <= 1;
            uartTx <= 0;// pull low to start
            if (txCounter == CYCLES_PER_BIT) begin
                txState <= TX_STATE_SEND;
                txCounter <= 1;
            end else begin
                txCounter <= txCounter + 1;
            end
        end
        TX_STATE_SEND_WAIT: begin
            txCounter <= txCounter + 1;
            if ((txCounter+1) == CYCLES_PER_BIT) begin
                txState <= TX_STATE_SEND;
            end
        end
        TX_STATE_SEND: begin
            txCounter <= 1;
            uartTx <= txData[txBitNumber];
            if (txData[txBitNumber]) begin // lsb to msb
                txParity <= ~txParity;
            end
            txBitNumber <= txBitNumber + 1;
            if (txBitNumber == 7) begin
                txState <=TX_STATE_PARITY_BIT;
            end else
                txState <= TX_STATE_SEND_WAIT;
        end
        TX_STATE_PARITY_BIT: begin
            txCounter <= txCounter + 1;
            if (txCounter==CYCLES_PER_BIT) begin
                uartTx <= txParity;
                txState <= TX_STATE_STOP_BIT;
                txCounter <= 1;
            end
        end
        TX_STATE_STOP_BIT: begin
            txCounter <= txCounter + 1;
            if (txCounter == CYCLES_PER_BIT) begin
                uartTx <= 1; // pull high for stop bit and return to idle state
                // we need to wait for another cycle...
                txState <= TX_STATE_STOP_DELAY;
                txCounter <= 1;
            end
        end
        TX_STATE_STOP_DELAY: begin
            txCounter <= txCounter+1;
            if (txCounter == CYCLES_PER_BIT) begin
                txCounter <= 1;
                txByteDone <= 1;
                txDataReady <= 0;
                txState <= TX_STATE_IDLE;
            end
        end
    endcase
end
always @(posedge clk) begin
    if (byteReady) begin
        led <= ~dataIn[5:0];
    end
end

always @(posedge btn1) begin
    txDataReady <= 1;
end
endmodule

uart/backup/uart_tb.v
module test();
  reg clk = 0;
  reg uart_rx = 1;
  wire uart_tx;
  wire [5:0] led;
  reg btn = 0; // Initialize low so we can pull it high later

  localparam BIT_PERIOD = 16;

  uart #(8'd8) u(
    clk,
    uart_rx,
    uart_tx,
    led,
    btn
  );

  always
    #1 clk = ~clk;

  // ---------------------------------------------------------
  // TASK: Send a UART byte (Simulating RX into the module)
  // ---------------------------------------------------------
  task send_byte;
    input [7:0] data;
    input parity_bit;
    integer i;
    begin
      // 1. Start bit
      uart_rx = 0;
      #(BIT_PERIOD);

      // 2. Data bits (LSB first)
      for (i = 0; i < 8; i = i + 1) begin
        uart_rx = data[i];
        #(BIT_PERIOD);
      end

      // 3. Parity bit
      uart_rx = parity_bit;
      #(BIT_PERIOD);

      // 4. Stop bit
      uart_rx = 1;
      #(BIT_PERIOD);

      // Idle time between bytes
      #(BIT_PERIOD * 2);
    end
  endtask

  // ---------------------------------------------------------
  // TASK: Capture a UART byte (Monitoring TX from the module)
  // ---------------------------------------------------------
  task capture_tx;
    reg [7:0] captured_data;
    reg captured_parity;
    integer i;
    begin
      // Wait for the start bit (falling edge on uart_tx)
      @(negedge uart_tx);

      // Delay by half a bit period to sample in the middle of the bit
      #(BIT_PERIOD / 2);

      if (uart_tx !== 0) $display("TX Error: Invalid start bit!");
      #(BIT_PERIOD);

      // Read 8 data bits
      for (i = 0; i < 8; i = i + 1) begin
        captured_data[i] = uart_tx;
        #(BIT_PERIOD);
      end

      // Read parity bit
      captured_parity = uart_tx;
      #(BIT_PERIOD);

      // Read stop bit
      if (uart_tx !== 1) $display("TX Error: Invalid stop bit!");

      $display($time, " | Captured TX Data: %b (0x%h) | TX Parity: %b",
               captured_data, captured_data, captured_parity);
    end
  endtask

  // ---------------------------------------------------------
  // MAIN TEST SEQUENCE
  // ---------------------------------------------------------
  initial begin
    $display("Starting EVEN Parity UART RX/TX Tests");
    $monitor($time, " | LED Value: %b | RX: %b | TX: %b | BTN: %b",
             led, uart_rx, uart_tx, btn);

    $dumpfile("uart.vcd");
    $dumpvars(0, test);

    // Initialize inputs
    uart_rx = 1;
    btn = 0;
    #20;

    // ==========================================
    // VALID DATA TESTS (Correct EVEN Parity)
    // ==========================================

    // --- Test 1: Original Byte ---
    $display("\n--- Test Case 1: 0x61 (01100001) - Valid EVEN Parity ---");
    // Three 1s (odd). Parity must be 1 to make the total even (4).
    send_byte(8'b01100001, 1'b1);

    // --- Test 2: Alternating Bits ---
    $display("\n--- Test Case 2: 0xA5 (10100101) - Valid EVEN Parity ---");
    // Four 1s (even). Parity must be 0 to keep the total even (4).
    send_byte(8'hA5, 1'b0);

    // --- Test 3: Boundary - All Ones ---
    $display("\n--- Test Case 3: 0xFF (11111111) - Valid EVEN Parity ---");
    // Eight 1s (even). Parity must be 0 to keep the total even (8).
    send_byte(8'hFF, 1'b0);

    // --- Test 4: Boundary - All Zeros ---
    $display("\n--- Test Case 4: 0x00 (00000000) - Valid EVEN Parity ---");
    // Zero 1s (even). Parity must be 0 to keep the total even (0).
    send_byte(8'h00, 1'b0);


    // ==========================================
    // ERROR TESTS (Bad EVEN Parity)
    // ==========================================

    // --- Test 5: Bad Parity on Alternating Bits ---
    $display("\n--- Test Case 5: 0x5A (01011010) - BAD EVEN Parity ---");
    // Four 1s. Correct even parity is 0. We intentionally send 1.
    // Total 1s = 5 (Odd). This should trigger an error in your module.
    send_byte(8'h5A, 1'b1);

    // --- Test 6: Bad Parity on All Zeros ---
    $display("\n--- Test Case 6: 0x00 (00000000) - BAD EVEN Parity ---");
    // Zero 1s. Correct even parity is 0. We intentionally send 1.
    // Total 1s = 1 (Odd). This should trigger an error.
    send_byte(8'h00, 1'b1);

    #(BIT_PERIOD * 4); // Breathing room before TX test


    // ==========================================
    // TX TEST (Triggered by Button)
    // ==========================================

    $display("\n--- Test Case 7: Pulling btn HIGH to trigger TX ---");

    fork
        // Thread 1: Start listening on the TX line immediately
        begin
        $display("Waiting for module to transmit on uart_tx...");
        capture_tx();
        end

        // Thread 2: Press and release the button
        begin
        btn = 1;
        #(BIT_PERIOD * 2);
        btn = 0;
        end
    join

    // Give the simulator a little time to settle after the stop bit
    #(BIT_PERIOD * 4);
    $display("\nTests Completed.");
    $finish;
  end

endmodule

uart/backup/uart.vcd
$date
	Fri Mar 27 18:11:42 2026
$end
$version
	Icarus Verilog
$end
$timescale
	1s
$end
$scope module test $end
$var wire 1 ! uart_tx $end
$var wire 6 " led [5:0] $end
$var parameter 32 # BIT_PERIOD $end
$var reg 1 $ btn $end
$var reg 1 % clk $end
$var reg 1 & uart_rx $end
$scope module u $end
$var wire 1 $ btn1 $end
$var wire 1 % clk $end
$var wire 1 & uartRx $end
$var parameter 8 ' CYCLES_PER_BIT $end
$var parameter 32 ( CYCLES_PER_READ $end
$var parameter 32 ) RX_STATE_IDLE $end
$var parameter 32 * RX_STATE_PARITY_BIT $end
$var parameter 32 + RX_STATE_READ $end
$var parameter 32 , RX_STATE_READ_WAIT $end
$var parameter 32 - RX_STATE_START_BIT $end
$var parameter 32 . RX_STATE_STOP_BIT $end
$var parameter 32 / TX_STATE_IDLE $end
$var parameter 32 0 TX_STATE_PARITY_BIT $end
$var parameter 32 1 TX_STATE_SEND $end
$var parameter 32 2 TX_STATE_SEND_WAIT $end
$var parameter 32 3 TX_STATE_START_BIT $end
$var parameter 32 4 TX_STATE_STOP_BIT $end
$var parameter 32 5 TX_STATE_STOP_DELAY $end
$var reg 1 6 byteGood $end
$var reg 1 7 byteReady $end
$var reg 8 8 data [7:0] $end
$var reg 8 9 dataIn [7:0] $end
$var reg 6 : led [5:0] $end
$var reg 3 ; rxBitNumber [2:0] $end
$var reg 13 < rxCounter [12:0] $end
$var reg 1 = rxParity $end
$var reg 4 > rxState [3:0] $end
$var reg 3 ? txBitNumber [2:0] $end
$var reg 1 @ txByteDone $end
$var reg 13 A txCounter [12:0] $end
$var reg 8 B txData [7:0] $end
$var reg 1 C txDataReady $end
$var reg 1 D txParity $end
$var reg 4 E txState [3:0] $end
$var reg 1 ! uartTx $end
$upscope $end
$scope task capture_tx $end
$var reg 8 F captured_data [7:0] $end
$var reg 1 G captured_parity $end
$var integer 32 H i [31:0] $end
$upscope $end
$scope task send_byte $end
$var reg 8 I data [7:0] $end
$var reg 1 J parity_bit $end
$var integer 32 K i [31:0] $end
$upscope $end
$upscope $end
$enddefinitions $end
$comment Show the parameter values. $end
$dumpall
b111 5
b110 4
b1 3
b10 2
b11 1
b101 0
b0 /
b110 .
b1 -
b10 ,
b11 +
b101 *
b0 )
b100 (
b1000 '
b10000 #
$end
#0
$dumpvars
bx K
xJ
bx I
bx H
xG
bx F
b0 E
0D
0C
b10101010 B
b0 A
0@
b0 ?
b0 >
0=
b0 <
b0 ;
bx :
b0 9
b0 8
07
06
1&
0%
0$
bx "
x!
$end
#1
1!
1%
#2
0%
#3
1%
#4
0%
#5
1%
#6
0%
#7
1%
#8
0%
#9
1%
#10
0%
#11
1%
#12
0%
#13
1%
#14
0%
#15
1%
#16
0%
#17
1%
#18
0%
#19
1%
#20
0%
0&
1J
b1100001 I
#21
b1 <
b1 >
1%
#22
0%
#23
b10 <
1%
#24
0%
#25
b11 <
1%
#26
0%
#27
b100 <
1%
#28
0%
#29
b1 <
b10 >
1%
#30
0%
#31
b10 <
1%
#32
0%
#33
b11 <
1%
#34
0%
#35
b100 <
1%
#36
0%
1&
b0 K
#37
b101 <
1%
#38
0%
#39
b110 <
1%
#40
0%
#41
b111 <
1%
#42
0%
#43
b11 >
b1000 <
1%
#44
0%
#45
b10 >
1=
b1 ;
b10000000 9
b1 <
1%
#46
0%
#47
b10 <
1%
#48
0%
#49
b11 <
1%
#50
0%
#51
b100 <
1%
#52
0%
0&
b1 K
#53
b101 <
1%
#54
0%
#55
b110 <
1%
#56
0%
#57
b111 <
1%
#58
0%
#59
b11 >
b1000 <
1%
#60
0%
#61
b10 >
b10 ;
b1000000 9
b1 <
1%
#62
0%
#63
b10 <
1%
#64
0%
#65
b11 <
1%
#66
0%
#67
b100 <
1%
#68
0%
b10 K
#69
b101 <
1%
#70
0%
#71
b110 <
1%
#72
0%
#73
b111 <
1%
#74
0%
#75
b11 >
b1000 <
1%
#76
0%
#77
b10 >
b11 ;
b100000 9
b1 <
1%
#78
0%
#79
b10 <
1%
#80
0%
#81
b11 <
1%
#82
0%
#83
b100 <
1%
#84
0%
b11 K
#85
b101 <
1%
#86
0%
#87
b110 <
1%
#88
0%
#89
b111 <
1%
#90
0%
#91
b11 >
b1000 <
1%
#92
0%
#93
b10 >
b100 ;
b10000 9
b1 <
1%
#94
0%
#95
b10 <
1%
#96
0%
#97
b11 <
1%
#98
0%
#99
b100 <
1%
#100
0%
b100 K
#101
b101 <
1%
#102
0%
#103
b110 <
1%
#104
0%
#105
b111 <
1%
#106
0%
#107
b11 >
b1000 <
1%
#108
0%
#109
b10 >
b101 ;
b1000 9
b1 <
1%
#110
0%
#111
b10 <
1%
#112
0%
#113
b11 <
1%
#114
0%
#115
b100 <
1%
#116
0%
1&
b101 K
#117
b101 <
1%
#118
0%
#119
b110 <
1%
#120
0%
#121
b111 <
1%
#122
0%
#123
b11 >
b1000 <
1%
#124
0%
#125
b10 >
0=
b110 ;
b10000100 9
b1 <
1%
#126
0%
#127
b10 <
1%
#128
0%
#129
b11 <
1%
#130
0%
#131
b100 <
1%
#132
0%
b110 K
#133
b101 <
1%
#134
0%
#135
b110 <
1%
#136
0%
#137
b111 <
1%
#138
0%
#139
b11 >
b1000 <
1%
#140
0%
#141
b10 >
1=
b111 ;
b11000010 9
b1 <
1%
#142
0%
#143
b10 <
1%
#144
0%
#145
b11 <
1%
#146
0%
#147
b100 <
1%
#148
0%
0&
b111 K
#149
b101 <
1%
#150
0%
#151
b110 <
1%
#152
0%
#153
b111 <
1%
#154
0%
#155
b11 >
b1000 <
1%
#156
0%
#157
b101 >
b0 ;
b1100001 9
b1 <
1%
#158
0%
#159
b10 <
1%
#160
0%
#161
b11 <
1%
#162
0%
#163
b100 <
1%
#164
0%
1&
b1000 K
#165
b101 <
1%
#166
0%
#167
b110 <
1%
#168
0%
#169
b111 <
1%
#170
0%
#171
b1000 <
1%
#172
0%
#173
b110 >
16
b1 <
1%
#174
0%
#175
b10 <
1%
#176
0%
#177
b11 <
1%
#178
0%
#179
b100 <
1%
#180
0%
#181
b101 <
1%
#182
0%
#183
b110 <
1%
#184
0%
#185
b111 <
1%
#186
0%
#187
b1000 <
1%
#188
0%
#189
b1100001 8
17
b0 >
b1 <
1%
#190
0%
#191
b11110 "
b11110 :
1%
#192
0%
#193
1%
#194
0%
#195
1%
#196
0%
#197
1%
#198
0%
#199
1%
#200
0%
#201
1%
#202
0%
#203
1%
#204
0%
#205
1%
#206
0%
#207
1%
#208
0%
#209
1%
#210
0%
#211
1%
#212
0%
#213
1%
#214
0%
#215
1%
#216
0%
#217
1%
#218
0%
#219
1%
#220
0%
#221
1%
#222
0%
#223
1%
#224
0%
#225
1%
#226
0%
#227
1%
#228
0%
0&
0J
b10100101 I
#229
0=
06
07
b1 >
1%
#230
0%
#231
b10 <
1%
#232
0%
#233
b11 <
1%
#234
0%
#235
b100 <
1%
#236
0%
#237
b0 9
b1 <
b10 >
1%
#238
0%
#239
b10 <
1%
#240
0%
#241
b11 <
1%
#242
0%
#243
b100 <
1%
#244
0%
1&
b0 K
#245
b101 <
1%
#246
0%
#247
b110 <
1%
#248
0%
#249
b111 <
1%
#250
0%
#251
b11 >
b1000 <
1%
#252
0%
#253
b10 >
1=
b1 ;
b10000000 9
b1 <
1%
#254
0%
#255
b10 <
1%
#256
0%
#257
b11 <
1%
#258
0%
#259
b100 <
1%
#260
0%
0&
b1 K
#261
b101 <
1%
#262
0%
#263
b110 <
1%
#264
0%
#265
b111 <
1%
#266
0%
#267
b11 >
b1000 <
1%
#268
0%
#269
b10 >
b10 ;
b1000000 9
b1 <
1%
#270
0%
#271
b10 <
1%
#272
0%
#273
b11 <
1%
#274
0%
#275
b100 <
1%
#276
0%
1&
b10 K
#277
b101 <
1%
#278
0%
#279
b110 <
1%
#280
0%
#281
b111 <
1%
#282
0%
#283
b11 >
b1000 <
1%
#284
0%
#285
b10 >
0=
b11 ;
b10100000 9
b1 <
1%
#286
0%
#287
b10 <
1%
#288
0%
#289
b11 <
1%
#290
0%
#291
b100 <
1%
#292
0%
0&
b11 K
#293
b101 <
1%
#294
0%
#295
b110 <
1%
#296
0%
#297
b111 <
1%
#298
0%
#299
b11 >
b1000 <
1%
#300
0%
#301
b10 >
b100 ;
b1010000 9
b1 <
1%
#302
0%
#303
b10 <
1%
#304
0%
#305
b11 <
1%
#306
0%
#307
b100 <
1%
#308
0%
b100 K
#309
b101 <
1%
#310
0%
#311
b110 <
1%
#312
0%
#313
b111 <
1%
#314
0%
#315
b11 >
b1000 <
1%
#316
0%
#317
b10 >
b101 ;
b101000 9
b1 <
1%
#318
0%
#319
b10 <
1%
#320
0%
#321
b11 <
1%
#322
0%
#323
b100 <
1%
#324
0%
1&
b101 K
#325
b101 <
1%
#326
0%
#327
b110 <
1%
#328
0%
#329
b111 <
1%
#330
0%
#331
b11 >
b1000 <
1%
#332
0%
#333
b10 >
1=
b110 ;
b10010100 9
b1 <
1%
#334
0%
#335
b10 <
1%
#336
0%
#337
b11 <
1%
#338
0%
#339
b100 <
1%
#340
0%
0&
b110 K
#341
b101 <
1%
#342
0%
#343
b110 <
1%
#344
0%
#345
b111 <
1%
#346
0%
#347
b11 >
b1000 <
1%
#348
0%
#349
b10 >
b111 ;
b1001010 9
b1 <
1%
#350
0%
#351
b10 <
1%
#352
0%
#353
b11 <
1%
#354
0%
#355
b100 <
1%
#356
0%
1&
b111 K
#357
b101 <
1%
#358
0%
#359
b110 <
1%
#360
0%
#361
b111 <
1%
#362
0%
#363
b11 >
b1000 <
1%
#364
0%
#365
b101 >
0=
b0 ;
b10100101 9
b1 <
1%
#366
0%
#367
b10 <
1%
#368
0%
#369
b11 <
1%
#370
0%
#371
b100 <
1%
#372
0%
0&
b1000 K
#373
b101 <
1%
#374
0%
#375
b110 <
1%
#376
0%
#377
b111 <
1%
#378
0%
#379
b1000 <
1%
#380
0%
#381
b110 >
16
b1 <
1%
#382
0%
#383
b10 <
1%
#384
0%
#385
b11 <
1%
#386
0%
#387
b100 <
1%
#388
0%
1&
#389
b101 <
1%
#390
0%
#391
b110 <
1%
#392
0%
#393
b111 <
1%
#394
0%
#395
b1000 <
1%
#396
0%
#397
b10100101 8
17
b0 >
b1 <
1%
#398
0%
#399
b11010 "
b11010 :
1%
#400
0%
#401
1%
#402
0%
#403
1%
#404
0%
#405
1%
#406
0%
#407
1%
#408
0%
#409
1%
#410
0%
#411
1%
#412
0%
#413
1%
#414
0%
#415
1%
#416
0%
#417
1%
#418
0%
#419
1%
#420
0%
#421
1%
#422
0%
#423
1%
#424
0%
#425
1%
#426
0%
#427
1%
#428
0%
#429
1%
#430
0%
#431
1%
#432
0%
#433
1%
#434
0%
#435
1%
#436
0%
0&
b11111111 I
#437
06
07
b1 >
1%
#438
0%
#439
b10 <
1%
#440
0%
#441
b11 <
1%
#442
0%
#443
b100 <
1%
#444
0%
#445
b0 9
b1 <
b10 >
1%
#446
0%
#447
b10 <
1%
#448
0%
#449
b11 <
1%
#450
0%
#451
b100 <
1%
#452
0%
1&
b0 K
#453
b101 <
1%
#454
0%
#455
b110 <
1%
#456
0%
#457
b111 <
1%
#458
0%
#459
b11 >
b1000 <
1%
#460
0%
#461
b10 >
1=
b1 ;
b10000000 9
b1 <
1%
#462
0%
#463
b10 <
1%
#464
0%
#465
b11 <
1%
#466
0%
#467
b100 <
1%
#468
0%
b1 K
#469
b101 <
1%
#470
0%
#471
b110 <
1%
#472
0%
#473
b111 <
1%
#474
0%
#475
b11 >
b1000 <
1%
#476
0%
#477
b10 >
0=
b10 ;
b11000000 9
b1 <
1%
#478
0%
#479
b10 <
1%
#480
0%
#481
b11 <
1%
#482
0%
#483
b100 <
1%
#484
0%
b10 K
#485
b101 <
1%
#486
0%
#487
b110 <
1%
#488
0%
#489
b111 <
1%
#490
0%
#491
b11 >
b1000 <
1%
#492
0%
#493
b10 >
1=
b11 ;
b11100000 9
b1 <
1%
#494
0%
#495
b10 <
1%
#496
0%
#497
b11 <
1%
#498
0%
#499
b100 <
1%
#500
0%
b11 K
#501
b101 <
1%
#502
0%
#503
b110 <
1%
#504
0%
#505
b111 <
1%
#506
0%
#507
b11 >
b1000 <
1%
#508
0%
#509
b10 >
0=
b100 ;
b11110000 9
b1 <
1%
#510
0%
#511
b10 <
1%
#512
0%
#513
b11 <
1%
#514
0%
#515
b100 <
1%
#516
0%
b100 K
#517
b101 <
1%
#518
0%
#519
b110 <
1%
#520
0%
#521
b111 <
1%
#522
0%
#523
b11 >
b1000 <
1%
#524
0%
#525
b10 >
1=
b101 ;
b11111000 9
b1 <
1%
#526
0%
#527
b10 <
1%
#528
0%
#529
b11 <
1%
#530
0%
#531
b100 <
1%
#532
0%
b101 K
#533
b101 <
1%
#534
0%
#535
b110 <
1%
#536
0%
#537
b111 <
1%
#538
0%
#539
b11 >
b1000 <
1%
#540
0%
#541
b10 >
0=
b110 ;
b11111100 9
b1 <
1%
#542
0%
#543
b10 <
1%
#544
0%
#545
b11 <
1%
#546
0%
#547
b100 <
1%
#548
0%
b110 K
#549
b101 <
1%
#550
0%
#551
b110 <
1%
#552
0%
#553
b111 <
1%
#554
0%
#555
b11 >
b1000 <
1%
#556
0%
#557
b10 >
1=
b111 ;
b11111110 9
b1 <
1%
#558
0%
#559
b10 <
1%
#560
0%
#561
b11 <
1%
#562
0%
#563
b100 <
1%
#564
0%
b111 K
#565
b101 <
1%
#566
0%
#567
b110 <
1%
#568
0%
#569
b111 <
1%
#570
0%
#571
b11 >
b1000 <
1%
#572
0%
#573
b101 >
0=
b0 ;
b11111111 9
b1 <
1%
#574
0%
#575
b10 <
1%
#576
0%
#577
b11 <
1%
#578
0%
#579
b100 <
1%
#580
0%
0&
b1000 K
#581
b101 <
1%
#582
0%
#583
b110 <
1%
#584
0%
#585
b111 <
1%
#586
0%
#587
b1000 <
1%
#588
0%
#589
b110 >
16
b1 <
1%
#590
0%
#591
b10 <
1%
#592
0%
#593
b11 <
1%
#594
0%
#595
b100 <
1%
#596
0%
1&
#597
b101 <
1%
#598
0%
#599
b110 <
1%
#600
0%
#601
b111 <
1%
#602
0%
#603
b1000 <
1%
#604
0%
#605
b11111111 8
17
b0 >
b1 <
1%
#606
0%
#607
b0 "
b0 :
1%
#608
0%
#609
1%
#610
0%
#611
1%
#612
0%
#613
1%
#614
0%
#615
1%
#616
0%
#617
1%
#618
0%
#619
1%
#620
0%
#621
1%
#622
0%
#623
1%
#624
0%
#625
1%
#626
0%
#627
1%
#628
0%
#629
1%
#630
0%
#631
1%
#632
0%
#633
1%
#634
0%
#635
1%
#636
0%
#637
1%
#638
0%
#639
1%
#640
0%
#641
1%
#642
0%
#643
1%
#644
0%
0&
b0 I
#645
06
07
b1 >
1%
#646
0%
#647
b10 <
1%
#648
0%
#649
b11 <
1%
#650
0%
#651
b100 <
1%
#652
0%
#653
b0 9
b1 <
b10 >
1%
#654
0%
#655
b10 <
1%
#656
0%
#657
b11 <
1%
#658
0%
#659
b100 <
1%
#660
0%
b0 K
#661
b101 <
1%
#662
0%
#663
b110 <
1%
#664
0%
#665
b111 <
1%
#666
0%
#667
b11 >
b1000 <
1%
#668
0%
#669
b10 >
b1 ;
b1 <
1%
#670
0%
#671
b10 <
1%
#672
0%
#673
b11 <
1%
#674
0%
#675
b100 <
1%
#676
0%
b1 K
#677
b101 <
1%
#678
0%
#679
b110 <
1%
#680
0%
#681
b111 <
1%
#682
0%
#683
b11 >
b1000 <
1%
#684
0%
#685
b10 >
b10 ;
b1 <
1%
#686
0%
#687
b10 <
1%
#688
0%
#689
b11 <
1%
#690
0%
#691
b100 <
1%
#692
0%
b10 K
#693
b101 <
1%
#694
0%
#695
b110 <
1%
#696
0%
#697
b111 <
1%
#698
0%
#699
b11 >
b1000 <
1%
#700
0%
#701
b10 >
b11 ;
b1 <
1%
#702
0%
#703
b10 <
1%
#704
0%
#705
b11 <
1%
#706
0%
#707
b100 <
1%
#708
0%
b11 K
#709
b101 <
1%
#710
0%
#711
b110 <
1%
#712
0%
#713
b111 <
1%
#714
0%
#715
b11 >
b1000 <
1%
#716
0%
#717
b10 >
b100 ;
b1 <
1%
#718
0%
#719
b10 <
1%
#720
0%
#721
b11 <
1%
#722
0%
#723
b100 <
1%
#724
0%
b100 K
#725
b101 <
1%
#726
0%
#727
b110 <
1%
#728
0%
#729
b111 <
1%
#730
0%
#731
b11 >
b1000 <
1%
#732
0%
#733
b10 >
b101 ;
b1 <
1%
#734
0%
#735
b10 <
1%
#736
0%
#737
b11 <
1%
#738
0%
#739
b100 <
1%
#740
0%
b101 K
#741
b101 <
1%
#742
0%
#743
b110 <
1%
#744
0%
#745
b111 <
1%
#746
0%
#747
b11 >
b1000 <
1%
#748
0%
#749
b10 >
b110 ;
b1 <
1%
#750
0%
#751
b10 <
1%
#752
0%
#753
b11 <
1%
#754
0%
#755
b100 <
1%
#756
0%
b110 K
#757
b101 <
1%
#758
0%
#759
b110 <
1%
#760
0%
#761
b111 <
1%
#762
0%
#763
b11 >
b1000 <
1%
#764
0%
#765
b10 >
b111 ;
b1 <
1%
#766
0%
#767
b10 <
1%
#768
0%
#769
b11 <
1%
#770
0%
#771
b100 <
1%
#772
0%
b111 K
#773
b101 <
1%
#774
0%
#775
b110 <
1%
#776
0%
#777
b111 <
1%
#778
0%
#779
b11 >
b1000 <
1%
#780
0%
#781
b101 >
b0 ;
b1 <
1%
#782
0%
#783
b10 <
1%
#784
0%
#785
b11 <
1%
#786
0%
#787
b100 <
1%
#788
0%
b1000 K
#789
b101 <
1%
#790
0%
#791
b110 <
1%
#792
0%
#793
b111 <
1%
#794
0%
#795
b1000 <
1%
#796
0%
#797
b110 >
16
b1 <
1%
#798
0%
#799
b10 <
1%
#800
0%
#801
b11 <
1%
#802
0%
#803
b100 <
1%
#804
0%
1&
#805
b101 <
1%
#806
0%
#807
b110 <
1%
#808
0%
#809
b111 <
1%
#810
0%
#811
b1000 <
1%
#812
0%
#813
b0 8
17
b0 >
b1 <
1%
#814
0%
#815
b111111 "
b111111 :
1%
#816
0%
#817
1%
#818
0%
#819
1%
#820
0%
#821
1%
#822
0%
#823
1%
#824
0%
#825
1%
#826
0%
#827
1%
#828
0%
#829
1%
#830
0%
#831
1%
#832
0%
#833
1%
#834
0%
#835
1%
#836
0%
#837
1%
#838
0%
#839
1%
#840
0%
#841
1%
#842
0%
#843
1%
#844
0%
#845
1%
#846
0%
#847
1%
#848
0%
#849
1%
#850
0%
#851
1%
#852
0%
0&
1J
b1011010 I
#853
06
07
b1 >
1%
#854
0%
#855
b10 <
1%
#856
0%
#857
b11 <
1%
#858
0%
#859
b100 <
1%
#860
0%
#861
b1 <
b10 >
1%
#862
0%
#863
b10 <
1%
#864
0%
#865
b11 <
1%
#866
0%
#867
b100 <
1%
#868
0%
b0 K
#869
b101 <
1%
#870
0%
#871
b110 <
1%
#872
0%
#873
b111 <
1%
#874
0%
#875
b11 >
b1000 <
1%
#876
0%
#877
b10 >
b1 ;
b1 <
1%
#878
0%
#879
b10 <
1%
#880
0%
#881
b11 <
1%
#882
0%
#883
b100 <
1%
#884
0%
1&
b1 K
#885
b101 <
1%
#886
0%
#887
b110 <
1%
#888
0%
#889
b111 <
1%
#890
0%
#891
b11 >
b1000 <
1%
#892
0%
#893
b10 >
1=
b10 ;
b10000000 9
b1 <
1%
#894
0%
#895
b10 <
1%
#896
0%
#897
b11 <
1%
#898
0%
#899
b100 <
1%
#900
0%
0&
b10 K
#901
b101 <
1%
#902
0%
#903
b110 <
1%
#904
0%
#905
b111 <
1%
#906
0%
#907
b11 >
b1000 <
1%
#908
0%
#909
b10 >
b11 ;
b1000000 9
b1 <
1%
#910
0%
#911
b10 <
1%
#912
0%
#913
b11 <
1%
#914
0%
#915
b100 <
1%
#916
0%
1&
b11 K
#917
b101 <
1%
#918
0%
#919
b110 <
1%
#920
0%
#921
b111 <
1%
#922
0%
#923
b11 >
b1000 <
1%
#924
0%
#925
b10 >
0=
b100 ;
b10100000 9
b1 <
1%
#926
0%
#927
b10 <
1%
#928
0%
#929
b11 <
1%
#930
0%
