uart/uart_rx.v
`default_nettype none

module uart_rx
#(
    parameter CYCLES_PER_BIT = 234
)
(
    input wire clk,
    input wire rx_pin,           // previously uartRx
    output reg [7:0] rx_data_out,// previously data
    output reg rx_data_ready,    // previously byteReady
    output reg rx_data_good      // previously byteGood
);

localparam CYCLES_PER_READ = (CYCLES_PER_BIT/2); // read at the middle of a bit in case of clock wonkyness

// rx registers
reg [3:0]  state = 0;          // state of the uart state machine (previously rxState)
reg [12:0] cycle_counter = 0;  // number of clock cycle in current rx (previously rxCounter)
reg [2:0]  bit_index = 0;      // number of rx data bits read since start bit (previously rxBitNumber)
reg [7:0]  rx_shift_reg = 0;   // 8 bit uart rx data (previously dataIn)
reg        parity_calc = 0;    // parity flip per 1 this is for odd parity (previously rxParity)

localparam STATE_IDLE = 0;
localparam STATE_START_BIT = 1;
localparam STATE_READ_WAIT = 2;
localparam STATE_READ = 3;
localparam STATE_PARITY_BIT = 5;
localparam STATE_STOP_BIT = 6;

always @(posedge clk) begin
    case (state)
        STATE_IDLE: begin
            if (rx_pin == 0) begin // reset if it's pulled low
                state <= STATE_START_BIT;
                cycle_counter <= 1; // we start the read clock counter
                bit_index <= 0;
                rx_data_ready <= 0; // no data is indeed not ready
                rx_data_good <= 0; // we don't know if the data is good or not
                parity_calc <= 0; // reset parity
            end
        end
        STATE_START_BIT: begin
            if (cycle_counter == CYCLES_PER_READ) begin
                state <= STATE_READ_WAIT;
                cycle_counter <= 1;
                rx_shift_reg <= 0;
            end else
                cycle_counter <= cycle_counter + 1;
        end
        STATE_READ_WAIT: begin
            cycle_counter <= cycle_counter + 1;
            if ((cycle_counter+1) == CYCLES_PER_BIT) begin
                state <= STATE_READ;
            end
        end
        STATE_READ: begin
            cycle_counter <= 1;
            rx_shift_reg <= {rx_pin, rx_shift_reg[7:1]};
            bit_index <= bit_index + 1;
            if (rx_pin == 1) begin
                parity_calc <= ~parity_calc;
            end
            if (bit_index == 7) begin
                state <= STATE_PARITY_BIT;
                // // rxState <= RX_STATE_STOP_BIT; // no parity bit
            end else
                state <= STATE_READ_WAIT;
        end
        STATE_PARITY_BIT: begin
            cycle_counter <= cycle_counter + 1;
            if (cycle_counter == CYCLES_PER_BIT) begin
                if (rx_pin == parity_calc) begin
                    rx_data_good <= 1;
                end
                state <= STATE_STOP_BIT;
                cycle_counter <= 1;
            end
        end
        STATE_STOP_BIT: begin
            cycle_counter <= cycle_counter + 1;
            if (cycle_counter == CYCLES_PER_BIT) begin
                state <= STATE_IDLE;
                rx_data_ready <= 1;
                cycle_counter <= 1;
                if (rx_data_good) begin
                    rx_data_out <= rx_shift_reg;
                end else begin
                    rx_data_out <= 0;
                end
            end
        end
    endcase
end

endmodule

uart/uart_tx.v
`default_nettype none

module uart_tx
#(
    parameter CYCLES_PER_BIT = 234
)
(
    input wire clk,
    input wire tx_start,         // 1-cycle pulse to start sending
    input wire [7:0] tx_data_in, // The byte you want to send
    output reg tx_pin,
    output reg tx_byte_done      // Pulses high when finished
);

// TX registers
reg [3:0]  state = 0;
reg [12:0] cycle_counter = 0;
reg [2:0]  bit_index = 0;
reg [7:0]  tx_data_reg = 0;   // Register to hold data while sending
reg        parity_calc = 0;

localparam  STATE_IDLE = 0;
localparam  STATE_START_BIT = 1;
localparam  STATE_SEND_WAIT = 2;
localparam  STATE_SEND = 3;
localparam  STATE_PARITY_BIT = 5;
localparam  STATE_STOP_BIT = 6;
localparam  STATE_STOP_DELAY = 7;

always @(posedge clk) begin
    case (state)
        STATE_IDLE: begin
            tx_pin <= 1;
            if (tx_start) begin
                state <= STATE_START_BIT;
                cycle_counter <= 1;
                bit_index <= 0;
                tx_byte_done <= 0;
                parity_calc <= 0;
                tx_data_reg <= tx_data_in; // Latch the incoming data so it doesn't change mid-send
            end
        end
        STATE_START_BIT: begin
            tx_pin <= 0; // pull low to start
            if (cycle_counter == CYCLES_PER_BIT) begin
                state <= STATE_SEND;
                cycle_counter <= 1;
            end else begin
                cycle_counter <= cycle_counter + 1;
            end
        end
        STATE_SEND_WAIT: begin
            cycle_counter <= cycle_counter + 1;
            if ((cycle_counter+1) == CYCLES_PER_BIT) begin
                state <= STATE_SEND;
            end
        end
        STATE_SEND: begin
            cycle_counter <= 1;
            tx_pin <= tx_data_reg[bit_index];
            if (tx_data_reg[bit_index]) begin // lsb to msb
                parity_calc <= ~parity_calc;
            end
            bit_index <= bit_index + 1;
            if (bit_index == 7) begin
                state <= STATE_PARITY_BIT;
            end else
                state <= STATE_SEND_WAIT;
        end
        STATE_PARITY_BIT: begin
            cycle_counter <= cycle_counter + 1;
            if (cycle_counter == CYCLES_PER_BIT) begin
                tx_pin <= parity_calc;
                state <= STATE_STOP_BIT;
                cycle_counter <= 1;
            end
        end
        STATE_STOP_BIT: begin
            cycle_counter <= cycle_counter + 1;
            if (cycle_counter == CYCLES_PER_BIT) begin
                tx_pin <= 1; // pull high for stop bit and return to idle state
                state <= STATE_STOP_DELAY;
                cycle_counter <= 1;
            end
        end
        STATE_STOP_DELAY: begin
            cycle_counter <= cycle_counter+1;
            if (cycle_counter == CYCLES_PER_BIT) begin
                cycle_counter <= 1;
                tx_byte_done <= 1; // Signal to the outside world we are done
                state <= STATE_IDLE;
            end
        end
    endcase
end

endmodule

uart/uart_top.v
`default_nettype none

module uart_top
#(
    parameter CYCLES_PER_BIT = 234
)
(
    // hardaware io
    input wire clk,
    input wire uartRx,
    output wire uartTx,
    output reg [5:0] led
);

// rx
wire [7:0] uart_rx_in; // DRIVEN BY SUBMODULES
wire rx_data_ready;
wire rx_data_good;

// tx
reg [7:0] uart_tx_out; // reg since driven by this
reg tx_start;
wire tx_done;

reg [3:0] state = 0;

uart_tx #(
    .CYCLES_PER_BIT(234)
) uart_tx_inst (
    .clk(clk),
    .tx_start(tx_start),
    .tx_data_in(uart_tx_out),
    .tx_pin(uartTx),
    .tx_byte_done(tx_done)
);

uart_rx #(
    .CYCLES_PER_BIT(234)
) uart_rx_inst (
    .clk(clk),
    .rx_data_out(uart_rx_in),
    .rx_pin(uartRx),
    .rx_data_ready(rx_data_ready),
    .rx_data_good(rx_data_good)
);


// fsm

localparam IDLE  = 0;
localparam START = 1;
localparam WAIT  = 2;


always @(posedge clk) begin
    case (state)
        IDLE: begin
            // if we have data form rx to send back
            if (rx_data_ready) begin
                uart_tx_out <= uart_rx_in;
                tx_start<=1;
                state<= START;
            end
        end
        START: begin
            tx_start <=0; // only pull it high for 1 cycle
            state <= WAIT;
        end
        WAIT: begin
            if (tx_done && ~rx_data_ready) begin // wait until next data rdy event
                state <= IDLE;
            end
        end
    endcase
end
endmodule

uart/uart_top_tb.v
`default_nettype none
`timescale 1ns/1ns
// this was ai generated
module test();

  // ---------------------------------------------------------
  // Signals & Parameters
  // ---------------------------------------------------------
  reg clk = 0;
  reg uartRx = 1;
  wire uartTx;
  wire [5:0] led;

  localparam CYCLES_PER_BIT = 234;
  localparam CLOCK_PERIOD = 2;
  localparam BIT_PERIOD = CYCLES_PER_BIT * CLOCK_PERIOD;

  // ---------------------------------------------------------
  // Device Under Test (DUT)
  // ---------------------------------------------------------
  uart_top #(
    .CYCLES_PER_BIT(CYCLES_PER_BIT)
  ) dut (
    .clk(clk),
    .uartRx(uartRx),
    .uartTx(uartTx),
    .led(led)
  );

  // Clock generation
  always #(CLOCK_PERIOD/2) clk = ~clk;

  // ---------------------------------------------------------
  // TASK: Send byte to the FPGA (Host -> FPGA)
  // ---------------------------------------------------------
  task send_byte;
    input [7:0] data;
    reg parity_bit;
    integer i;
    begin
      // XOR reduction calculates the EVEN parity bit automatically
      parity_bit = ^data;
      $display($time, " | [HOST TX] Sending data: 8'h%h | Parity: %b", data, parity_bit);

      // 1. Start bit
      uartRx = 0;
      #(BIT_PERIOD);

      // 2. Data bits (LSB first)
      for (i = 0; i < 8; i = i + 1) begin
        uartRx = data[i];
        #(BIT_PERIOD);
      end

      // 3. Parity bit (EVEN)
      uartRx = parity_bit;
      #(BIT_PERIOD);

      // 4. Stop bit
      uartRx = 1;
      #(BIT_PERIOD);
    end
  endtask

  // ---------------------------------------------------------
  // TASK: Monitor and verify echoed byte (FPGA -> Host)
  // ---------------------------------------------------------
  task expect_byte;
    input [7:0] expected_data;
    reg [7:0] captured_data;
    reg captured_parity;
    reg expected_parity;
    integer i;
    begin
      // What the parity bit *should* be
      expected_parity = ^expected_data;

      // Wait for the start bit (falling edge on uartTx)
      @(negedge uartTx);

      // Delay by half a bit period to sample in the middle of the bit
      #(BIT_PERIOD / 2);

      if (uartTx !== 0) $display($time, " | [HOST RX] Error: Invalid start bit!");
      #(BIT_PERIOD);

      // Read 8 data bits
      for (i = 0; i < 8; i = i + 1) begin
        captured_data[i] = uartTx;
        #(BIT_PERIOD);
      end

      // Read parity bit
      captured_parity = uartTx;
      #(BIT_PERIOD);

      // Read stop bit
      if (uartTx !== 1) $display($time, " | [HOST RX] Error: Invalid stop bit!");

      // Verify the echo (Both Data and Parity must match)
      if ((captured_data === expected_data) && (captured_parity === expected_parity))
        $display($time, " | [HOST RX] SUCCESS: Echo matched! Received: 8'%b | Parity: %b",
                 captured_data, captured_parity);
      else
        $display($time, " | [HOST RX] FAIL: Expected 8'b%b (Parity %b), but got 8'b%b (Parity %b)",
                 expected_data, expected_parity, captured_data, captured_parity);
    end
  endtask

  // ---------------------------------------------------------
  // TASK: Wrapper to test a full echo cycle concurrently
  // ---------------------------------------------------------
  task run_echo_test;
    input [7:0] test_data;
    begin
      fork
        // Thread 1: Send the data
        send_byte(test_data);

        // Thread 2: Receive and verify the echo
        expect_byte(test_data);
      join

      // Idle time between tests
      #(BIT_PERIOD * 6);
    end
  endtask

  // ---------------------------------------------------------
  // MAIN TEST SEQUENCE
  // ---------------------------------------------------------
  initial begin
    $display("Starting EVEN Parity UART Echo Tests");
    $dumpfile("uart_echo.vcd");
    $dumpvars(0, test);

    // Initialize
    uartRx = 1;
    #(BIT_PERIOD * 2);

    // Run Echo Tests
    $display("\n--- Test 1: Echo 0x55 (Alternating 01010101) ---");
    run_echo_test(8'h55);

    $display("\n--- Test 2: Echo 0xAA (Alternating 10101010) ---");
    run_echo_test(8'hAA);

    $display("\n--- Test 3: Echo 0x00 (All Zeros) ---");
    run_echo_test(8'h00);

    $display("\n--- Test 4: Echo 0xFF (All Ones) ---");
    run_echo_test(8'hFF);

    $display("\n--- Test 5: Echo 0x4A (Random Data) ---");
    run_echo_test(8'h4A);

    $display("\nTests Completed.");
    $finish;
  end

endmodule

uart/uart_echo.vcd
$date
	Sat Mar 28 16:37:57 2026
$end
$version
	Icarus Verilog
$end
$timescale
	1ns
$end
$scope module test $end
$var wire 1 ! uartTx $end
$var wire 6 " led [5:0] $end
$var parameter 64 # BIT_PERIOD $end
$var parameter 32 $ CLOCK_PERIOD $end
$var parameter 32 % CYCLES_PER_BIT $end
$var reg 1 & clk $end
$var reg 1 ' uartRx $end
$scope module dut $end
$var wire 1 & clk $end
$var wire 1 ' uartRx $end
$var wire 8 ( uart_rx_in [7:0] $end
$var wire 1 ! uartTx $end
$var wire 1 ) tx_done $end
$var wire 1 * rx_data_ready $end
$var wire 1 + rx_data_good $end
$var parameter 32 , CYCLES_PER_BIT $end
$var parameter 32 - IDLE $end
$var parameter 32 . START $end
$var parameter 32 / WAIT $end
$var reg 6 0 led [5:0] $end
$var reg 4 1 state [3:0] $end
$var reg 1 2 tx_start $end
$var reg 8 3 uart_tx_out [7:0] $end
$scope module uart_rx_inst $end
$var wire 1 & clk $end
$var wire 1 ' rx_pin $end
$var parameter 32 4 CYCLES_PER_BIT $end
$var parameter 32 5 CYCLES_PER_READ $end
$var parameter 32 6 STATE_IDLE $end
$var parameter 32 7 STATE_PARITY_BIT $end
$var parameter 32 8 STATE_READ $end
$var parameter 32 9 STATE_READ_WAIT $end
$var parameter 32 : STATE_START_BIT $end
$var parameter 32 ; STATE_STOP_BIT $end
$var reg 3 < bit_index [2:0] $end
$var reg 13 = cycle_counter [12:0] $end
$var reg 1 > parity_calc $end
$var reg 1 + rx_data_good $end
$var reg 8 ? rx_data_out [7:0] $end
$var reg 1 * rx_data_ready $end
$var reg 8 @ rx_shift_reg [7:0] $end
$var reg 4 A state [3:0] $end
$upscope $end
$scope module uart_tx_inst $end
$var wire 1 & clk $end
$var wire 8 B tx_data_in [7:0] $end
$var wire 1 2 tx_start $end
$var parameter 32 C CYCLES_PER_BIT $end
$var parameter 32 D STATE_IDLE $end
$var parameter 32 E STATE_PARITY_BIT $end
$var parameter 32 F STATE_SEND $end
$var parameter 32 G STATE_SEND_WAIT $end
$var parameter 32 H STATE_START_BIT $end
$var parameter 32 I STATE_STOP_BIT $end
$var parameter 32 J STATE_STOP_DELAY $end
$var reg 3 K bit_index [2:0] $end
$var reg 13 L cycle_counter [12:0] $end
$var reg 1 M parity_calc $end
$var reg 4 N state [3:0] $end
$var reg 1 ) tx_byte_done $end
$var reg 8 O tx_data_reg [7:0] $end
$var reg 1 ! tx_pin $end
$upscope $end
$upscope $end
$scope task expect_byte $end
$var reg 8 P captured_data [7:0] $end
$var reg 1 Q captured_parity $end
$var reg 8 R expected_data [7:0] $end
$var reg 1 S expected_parity $end
$var integer 32 T i [31:0] $end
$upscope $end
$scope task run_echo_test $end
$var reg 8 U test_data [7:0] $end
$upscope $end
$scope task send_byte $end
$var reg 8 V data [7:0] $end
$var reg 1 W parity_bit $end
$var integer 32 X i [31:0] $end
$upscope $end
$upscope $end
$enddefinitions $end
$comment Show the parameter values. $end
$dumpall
b111 J
b110 I
b1 H
b10 G
b11 F
b101 E
b0 D
b11101010 C
b110 ;
b1 :
b10 9
b11 8
b101 7
b0 6
b1110101 5
b11101010 4
b10 /
b1 .
b0 -
b11101010 ,
b11101010 %
b10 $
b111010100 #
$end
#0
$dumpvars
bx X
xW
bx V
bx U
bx T
xS
bx R
xQ
bx P
b0 O
b0 N
0M
b0 L
b0 K
bx B
b0 A
b0 @
bx ?
0>
b0 =
b0 <
bx 3
x2
b0 1
bx 0
x+
x*
x)
bx (
1'
0&
bx "
x!
$end
#1
1!
1&
#2
0&
#3
1&
#4
0&
#5
1&
#6
0&
#7
1&
#8
0&
#9
1&
#10
0&
#11
1&
#12
0&
#13
1&
#14
0&
#15
1&
#16
0&
#17
1&
#18
0&
#19
1&
#20
0&
#21
1&
#22
0&
#23
1&
#24
0&
#25
1&
#26
0&
#27
1&
#28
0&
#29
1&
#30
0&
#31
1&
#32
0&
#33
1&
#34
0&
#35
1&
#36
0&
#37
1&
#38
0&
#39
1&
#40
0&
#41
1&
#42
0&
#43
1&
#44
0&
#45
1&
#46
0&
#47
1&
#48
0&
#49
1&
#50
0&
#51
1&
#52
0&
#53
1&
#54
0&
#55
1&
#56
0&
#57
1&
#58
0&
#59
1&
#60
0&
#61
1&
#62
0&
#63
1&
#64
0&
#65
1&
#66
0&
#67
1&
#68
0&
#69
1&
#70
0&
#71
1&
#72
0&
#73
1&
#74
0&
#75
1&
#76
0&
#77
1&
#78
0&
#79
1&
#80
0&
#81
1&
#82
0&
#83
1&
#84
0&
#85
1&
#86
0&
#87
1&
#88
0&
#89
1&
#90
0&
#91
1&
#92
0&
#93
1&
#94
0&
#95
1&
#96
0&
#97
1&
#98
0&
#99
1&
#100
0&
#101
1&
#102
0&
#103
1&
#104
0&
#105
1&
#106
0&
#107
1&
#108
0&
#109
1&
#110
0&
#111
1&
#112
0&
#113
1&
#114
0&
#115
1&
#116
0&
#117
1&
#118
0&
#119
1&
#120
0&
#121
1&
#122
0&
#123
1&
#124
0&
#125
1&
#126
0&
#127
1&
#128
0&
#129
1&
#130
0&
#131
1&
#132
0&
#133
1&
#134
0&
#135
1&
#136
0&
#137
1&
#138
0&
#139
1&
#140
0&
#141
1&
#142
0&
#143
1&
#144
0&
#145
1&
#146
0&
#147
1&
#148
0&
#149
1&
#150
0&
#151
1&
#152
0&
#153
1&
#154
0&
#155
1&
#156
0&
#157
1&
#158
0&
#159
1&
#160
0&
#161
1&
#162
0&
#163
1&
#164
0&
#165
1&
#166
0&
#167
1&
#168
0&
#169
1&
#170
0&
#171
1&
#172
0&
#173
1&
#174
0&
#175
1&
#176
0&
#177
1&
#178
0&
#179
1&
#180
0&
#181
1&
#182
0&
#183
1&
#184
0&
#185
1&
#186
0&
#187
1&
#188
0&
#189
1&
#190
0&
#191
1&
#192
0&
#193
1&
#194
0&
#195
1&
#196
0&
#197
1&
#198
0&
#199
1&
#200
0&
#201
1&
#202
0&
#203
1&
#204
0&
#205
1&
#206
0&
#207
1&
#208
0&
#209
1&
#210
0&
#211
1&
#212
0&
#213
1&
#214
0&
#215
1&
#216
0&
#217
1&
#218
0&
#219
1&
#220
0&
#221
1&
#222
0&
#223
1&
#224
0&
#225
1&
#226
0&
#227
1&
#228
0&
#229
1&
#230
0&
#231
1&
#232
0&
#233
1&
#234
0&
#235
1&
#236
0&
#237
1&
#238
0&
#239
1&
#240
0&
#241
1&
#242
0&
#243
1&
#244
0&
#245
1&
#246
0&
#247
1&
#248
0&
#249
1&
#250
0&
#251
1&
#252
0&
#253
1&
#254
0&
#255
1&
#256
0&
#257
1&
#258
0&
#259
1&
#260
0&
#261
1&
#262
0&
#263
1&
#264
0&
#265
1&
#266
0&
#267
1&
#268
0&
#269
1&
#270
0&
#271
1&
#272
0&
#273
1&
#274
0&
#275
1&
#276
0&
#277
1&
#278
0&
#279
1&
#280
0&
#281
1&
#282
0&
#283
1&
#284
0&
#285
1&
#286
0&
#287
1&
#288
0&
#289
1&
#290
0&
#291
1&
#292
0&
#293
1&
#294
0&
#295
1&
#296
0&
#297
1&
#298
0&
#299
1&
#300
0&
#301
1&
#302
0&
#303
1&
#304
0&
#305
1&
#306
0&
#307
1&
#308
0&
#309
1&
#310
0&
#311
1&
#312
0&
#313
1&
#314
0&
#315
1&
#316
0&
#317
1&
#318
0&
#319
1&
#320
0&
#321
1&
#322
0&
#323
1&
#324
0&
#325
1&
#326
0&
#327
1&
#328
0&
#329
1&
#330
0&
#331
1&
#332
0&
#333
1&
#334
0&
#335
1&
#336
0&
#337
1&
#338
0&
#339
1&
#340
0&
#341
1&
#342
0&
#343
1&
#344
0&
#345
1&
#346
0&
#347
1&
#348
0&
#349
1&
#350
0&
#351
1&
#352
0&
#353
1&
#354
0&
#355
1&
#356
0&
#357
1&
#358
0&
#359
1&
#360
0&
#361
1&
#362
0&
#363
1&
#364
0&
#365
1&
#366
0&
#367
1&
#368
0&
#369
1&
#370
0&
#371
1&
#372
0&
#373
1&
#374
0&
#375
1&
#376
0&
#377
1&
#378
0&
#379
1&
#380
0&
#381
1&
#382
0&
#383
1&
#384
0&
#385
1&
#386
0&
#387
1&
#388
0&
#389
1&
#390
0&
#391
1&
#392
0&
#393
1&
#394
0&
#395
1&
#396
0&
#397
1&
#398
0&
#399
1&
#400
0&
#401
1&
#402
0&
#403
1&
#404
0&
#405
1&
#406
0&
#407
1&
#408
0&
#409
1&
#410
0&
#411
1&
#412
0&
#413
1&
#414
0&
#415
1&
#416
0&
#417
1&
#418
0&
#419
1&
#420
0&
#421
1&
#422
0&
#423
1&
#424
0&
#425
1&
#426
0&
#427
1&
#428
0&
#429
1&
#430
0&
#431
1&
#432
0&
#433
1&
#434
0&
#435
1&
#436
0&
#437
1&
#438
0&
#439
1&
#440
0&
#441
1&
#442
0&
#443
1&
#444
0&
#445
1&
#446
0&
#447
1&
#448
0&
#449
1&
#450
0&
#451
1&
#452
0&
#453
1&
#454
0&
#455
1&
#456
0&
#457
1&
#458
0&
#459
1&
#460
0&
#461
1&
#462
0&
#463
1&
#464
0&
#465
1&
#466
0&
#467
1&
#468
0&
#469
1&
#470
0&
#471
1&
#472
0&
#473
1&
#474
0&
#475
1&
#476
0&
#477
1&
#478
0&
#479
1&
#480
0&
#481
1&
#482
0&
#483
1&
#484
0&
#485
1&
#486
0&
#487
1&
#488
0&
#489
1&
#490
0&
#491
1&
#492
0&
#493
1&
#494
0&
#495
1&
#496
0&
#497
1&
#498
0&
#499
1&
#500
0&
#501
1&
#502
0&
#503
1&
#504
0&
#505
1&
#506
0&
#507
1&
#508
0&
#509
1&
#510
0&
#511
1&
#512
0&
#513
1&
#514
0&
#515
1&
#516
0&
#517
1&
#518
0&
#519
1&
#520
0&
#521
1&
#522
0&
#523
1&
#524
0&
#525
1&
#526
0&
#527
1&
#528
0&
#529
1&
#530
0&
#531
1&
#532
0&
#533
1&
#534
0&
#535
1&
#536
0&
#537
1&
#538
0&
#539
1&
#540
0&
#541
1&
#542
0&
#543
1&
#544
0&
#545
1&
#546
0&
#547
1&
#548
0&
#549
1&
#550
0&
#551
1&
#552
0&
#553
1&
#554
0&
#555
1&
#556
0&
#557
1&
#558
0&
#559
1&
#560
0&
#561
1&
#562
0&
#563
1&
#564
0&
#565
1&
#566
0&
#567
1&
#568
0&
#569
1&
#570
0&
#571
1&
#572
0&
#573
1&
#574
0&
#575
1&
#576
0&
#577
1&
#578
0&
#579
1&
#580
0&
#581
1&
#582
0&
#583
1&
#584
0&
#585
1&
#586
0&
#587
1&
#588
0&
#589
1&
#590
0&
#591
1&
#592
0&
#593
1&
#594
0&
#595
1&
#596
0&
#597
1&
#598
0&
#599
1&
#600
0&
#601
1&
#602
0&
#603
1&
#604
0&
#605
1&
#606
0&
#607
1&
#608
0&
#609
1&
#610
0&
#611
1&
#612
0&
#613
1&
#614
0&
#615
1&
#616
0&
#617
1&
#618
0&
#619
1&
#620
0&
#621
1&
#622
0&
#623
1&
#624
0&
#625
1&
#626
0&
#627
1&
#628
0&
#629
1&
#630
0&
#631
1&
#632
0&
#633
1&
#634
0&
#635
1&
#636
0&
#637
1&
#638
0&
#639
1&
#640
0&
#641
1&
#642
0&
#643
1&
#644
0&
#645
1&
#646
0&
#647
1&
#648
0&
#649
1&
#650
0&
#651
1&
#652
0&
#653
1&
#654
0&
#655
1&
#656
0&
#657
1&
#658
0&
#659
1&
#660
0&
#661
1&
#662
0&
#663
1&
#664
0&
#665
1&
#666
0&
#667
1&
#668
0&
#669
1&
#670
0&
#671
1&
#672
0&
#673
1&
#674
0&
#675
1&
#676
0&
#677
1&
#678
0&
#679
1&
#680
0&
#681
1&
#682
0&
#683
1&
#684
0&
#685
1&
#686
0&
#687
1&
#688
0&
#689
1&
#690
0&
#691
1&
#692
0&
#693
1&
#694
0&
#695
1&
#696
0&
#697
1&
#698
0&
#699
1&
#700
0&
#701
1&
#702
0&
#703
1&
#704
0&
#705
1&
#706
0&
#707
1&
#708
0&
#709
1&
#710
0&
#711
1&
#712
0&
#713
1&
#714
0&
#715
1&
#716
0&
#717
1&
#718
0&
#719
1&
#720
0&
#721
1&
#722
0&
#723
1&
#724
0&
#725
1&
#726
0&
#727
1&
#728
0&
#729
1&
#730
0&
#731
1&
#732
0&
#733
1&
#734
0&
#735
1&
#736
0&
#737
1&
#738
0&
#739
1&
#740
0&
#741
1&
#742
0&
#743
1&
#744
0&
#745
1&
#746
0&
#747
1&
#748
0&
#749
1&
#750
0&
#751
1&
#752
0&
#753
1&
#754
0&
#755
1&
#756
0&
#757
1&
#758
0&
#759
1&
#760
0&
#761
1&
#762
0&
#763
1&
#764
0&
#765
1&
#766
0&
#767
1&
#768
0&
#769
1&
#770
0&
#771
1&
#772
0&
#773
1&
#774
0&
#775
1&
#776
0&
#777
1&
#778
0&
#779
1&
#780
0&
#781
1&
#782
0&
#783
1&
#784
0&
#785
1&
#786
0&
#787
1&
#788
0&
#789
1&
#790
0&
#791
1&
#792
0&
#793
1&
#794
0&
#795
1&
#796
0&
#797
1&
#798
0&
#799
1&
#800
0&
#801
1&
#802
0&
#803
1&
#804
0&
#805
1&
#806
0&
#807
1&
#808
0&
#809
1&
#810
0&
#811
1&
#812
0&
#813
1&
#814
0&
#815
1&
#816
0&
#817
1&
#818
0&
#819
1&
#820
0&
#821
1&
#822
0&
#823
1&
#824
0&
#825
1&
#826
0&
#827
1&
#828
0&
#829
1&
#830
0&
#831
1&
#832
0&
#833
1&
#834
0&
#835
1&
#836
0&
#837
1&
#838
0&
#839
1&
#840
0&
#841
1&
#842
0&
#843
1&
#844
0&
#845
1&
#846
0&
#847
1&
#848
0&
#849
1&
#850
0&
#851
1&
#852
0&
#853
1&
#854
0&
#855
1&
#856
0&
#857
1&
#858
0&
#859
1&
#860
0&
#861
1&
#862
0&
#863
1&
#864
0&
#865
1&
#866
0&
#867
1&
#868
0&
#869
1&
#870
0&
#871
1&
#872
0&
#873
1&
#874
0&
#875
1&
#876
0&
#877
1&
#878
0&
#879
1&
#880
0&
#881
1&
#882
0&
#883
1&
#884
0&
#885
1&
#886
0&
#887
1&
#888
0&
#889
1&
#890
0&
#891
1&
#892
0&
#893
1&
#894
0&
#895
1&
#896
0&
#897
1&
#898
0&
#899
1&
#900
0&
#901
1&
#902
0&
#903
1&
#904
0&
#905
1&
#906
0&
#907
1&
#908
0&
#909
1&
#910
0&
#911
1&
#912
0&
#913
1&
#914
0&
#915
1&
#916
0&
#917
1&
#918
0&
#919
1&
#920
0&
#921
1&
#922
0&
#923
1&
#924
0&
#925
1&
#926
0&
#927
1&
#928
0&
#929
1&
#930
0&
#931
1&
#932
0&
#933
1&
#934
0&
#935
1&
#936
0&
0'
0W
b1010101 V
0S
b1010101 R
b1010101 U
#937
0+
0*
b1 =
b1 A
1&
#938
0&
#939
b10 =
1&
#940
0&
#941
b11 =
1&
#942
0&
#943
b100 =
1&
#944
0&
#945
b101 =
1&
#946
0&
#947
b110 =
1&
#948
0&
#949
b111 =
1&
#950
0&
#951
b1000 =
1&
#952
0&
#953
b1001 =
1&
#954
0&
#955
b1010 =
1&
#956
0&
#957
b1011 =
1&
#958
0&
#959
b1100 =
1&
#960
0&
#961
b1101 =
1&
#962
0&
#963
b1110 =
1&
#964
0&
#965
b1111 =
1&
#966
0&
#967
b10000 =
1&
#968
0&
#969
b10001 =
1&
#970
0&
#971
b10010 =
1&
#972
0&
#973
b10011 =
1&
#974
0&
#975
b10100 =
1&
#976
0&
#977
b10101 =
1&
#978
0&
#979
b10110 =
1&
#980
0&
#981
b10111 =
1&
#982
0&
#983
b11000 =
1&
#984
0&
#985
b11001 =
1&
#986
0&
#987
b11010 =
1&
#988
0&
#989
b11011 =
1&
#990
0&
#991
b11100 =
1&
#992
0&
#993
b11101 =
1&
#994
0&
#995
b11110 =
1&
#996
0&
#997
b11111 =
1&
#998
0&
#999
b100000 =
1&
#1000
0&
#1001
b100001 =
1&
#1002
0&
#1003
b100010 =
1&
#1004
0&
#1005
b100011 =
1&
#1006
0&
#1007
b100100 =
1&
#1008
0&
#1009
b100101 =
1&
#1010
0&
#1011
b100110 =
1&
#1012
0&
#1013
b100111 =
1&
#1014
0&
#1015
b101000 =
1&
#1016
0&
#1017
b101001 =
1&
#1018
0&
#1019
b101010 =
1&
#1020
0&
#1021
b101011 =
1&
#1022
0&
#1023
b101100 =
1&
#1024
0&
#1025
b101101 =
1&
#1026
0&
#1027
b101110 =
1&
#1028
0&
#1029
b101111 =
1&
#1030
0&
#1031
b110000 =
1&
#1032
0&
#1033
b110001 =
1&
#1034
0&
#1035
b110010 =
1&
#1036
0&
#1037
b110011 =
1&
#1038
0&
#1039
b110100 =
1&
#1040
0&
#1041
b110101 =
1&
#1042
0&
#1043
b110110 =
1&
#1044
0&
#1045
b110111 =
1&
#1046
0&
#1047
b111000 =
1&
#1048
0&
#1049
b111001 =
1&
#1050
0&
#1051
b111010 =
1&
#1052
0&
#1053
b111011 =
1&
#1054
0&
#1055
b111100 =
1&
#1056
0&
#1057
b111101 =
1&
#1058
0&
#1059
b111110 =
1&
#1060
0&
#1061
b111111 =
1&
#1062
0&
#1063
b1000000 =
1&
#1064
0&
#1065
b1000001 =
1&
#1066
0&
#1067
b1000010 =
1&
#1068
0&
#1069
b1000011 =
1&
#1070
0&
#1071
b1000100 =
1&
#1072
0&
#1073
b1000101 =
1&
#1074
0&
#1075
b1000110 =
1&
#1076
0&
#1077
b1000111 =
1&
#1078
0&
#1079
b1001000 =
1&
#1080
0&
#1081
b1001001 =
1&
#1082
0&
#1083
b1001010 =
1&
#1084
0&
#1085
b1001011 =
1&
#1086
0&
#1087
b1001100 =
1&
#1088
0&
#1089
b1001101 =
1&
#1090
0&
#1091
b1001110 =
1&
#1092
0&
#1093
b1001111 =
1&
#1094
0&
#1095
b1010000 =
1&
#1096
0&
#1097
b1010001 =
1&
#1098
0&
#1099
b1010010 =
1&
#1100
0&
#1101
b1010011 =
1&
#1102
0&
#1103
b1010100 =
1&
#1104
0&
#1105
b1010101 =
1&
#1106
0&
#1107
b1010110 =
1&
#1108
0&
#1109
b1010111 =
1&
#1110
0&
#1111
b1011000 =
1&
#1112
0&
#1113
b1011001 =
1&
#1114
0&
#1115
b1011010 =
1&
#1116
0&
#1117
b1011011 =
1&
#1118
0&
#1119
b1011100 =
1&
#1120
0&
#1121
b1011101 =
1&
#1122
0&
#1123
b1011110 =
1&
#1124
0&
#1125
b1011111 =
1&
#1126
0&
#1127
b1100000 =
1&
#1128
0&
#1129
b1100001 =
1&
#1130
0&
#1131
b1100010 =
1&
#1132
0&
#1133
b1100011 =
1&
#1134
0&
#1135
b1100100 =
1&
#1136
0&
#1137
b1100101 =
1&
#1138
0&
#1139
b1100110 =
1&
#1140
0&
#1141
b1100111 =
1&
#1142
0&
#1143
b1101000 =
1&
#1144
0&
#1145
b1101001 =
1&
#1146
0&
#1147
b1101010 =
1&
#1148
0&
#1149
b1101011 =
1&
#1150
0&
#1151
b1101100 =
1&
#1152
0&
#1153
b1101101 =
1&
#1154
0&
#1155
b1101110 =
1&
#1156
0&
#1157
b1101111 =
1&
#1158
0&
#1159
b1110000 =
1&
#1160
0&
#1161
b1110001 =
1&
#1162
0&
